{
  "_v": "1",
  "date": "2021-05-20",
  "zhDayOfTheWeek": "四",
  "headers": [
    "curr_load",
    "curr_util_rate",
    "fore_maxi_sply_capacity",
    "fore_peak_dema_load",
    "fore_peak_resv_capacity",
    "fore_peak_resv_rate",
    "fore_peak_resv_indicator",
    "fore_peak_hour_range",
    "publish_time",
    "yday_date",
    "yday_maxi_sply_capacity",
    "yday_peak_dema_load",
    "yday_peak_resv_capacity",
    "yday_peak_resv_rate",
    "yday_peak_resv_indicator"
  ],
  "data": [
    [
      "3088.5",
      "76",
      "4030.0",
      "3780.0",
      "250.0",
      "6.61",
      "Y",
      "13:00-16:00",
      "110.05.20(四)00:00",
      "110.05.19",
      "4038.3",
      "3728.8",
      "309.5",
      "8.30",
      "Y"
    ],
    [
      "3033.4",
      "75",
      "4030.0",
      "3780.0",
      "250.0",
      "6.61",
      "Y",
      "13:00-16:00",
      "110.05.20(四)00:10",
      "110.05.19",
      "4038.3",
      "3728.8",
      "309.5",
      "8.30",
      "Y"
    ],
    [
      "3027.0",
      "75",
      "4030.0",
      "3780.0",
      "250.0",
      "6.61",
      "Y",
      "13:00-16:00",
      "110.05.20(四)00:20",
      "110.05.19",
      "4038.3",
      "3728.8",
      "309.5",
      "8.30",
      "Y"
    ],
    [
      "3004.9",
      "74",
      "4030.0",
      "3780.0",
      "250.0",
      "6.61",
      "Y",
      "13:00-16:00",
      "110.05.20(四)00:30",
      "110.05.19",
      "4038.3",
      "3728.8",
      "309.5",
      "8.30",
      "Y"
    ],
    [
      "2972.6",
      "73",
      "4030.0",
      "3780.0",
      "250.0",
      "6.61",
      "Y",
      "13:00-16:00",
      "110.05.20(四)00:40",
      "110.05.19",
      "4038.3",
      "3728.8",
      "309.5",
      "8.30",
      "Y"
    ],
    [
      "2972.3",
      "73",
      "4030.0",
      "3780.0",
      "250.0",
      "6.61",
      "Y",
      "13:00-16:00",
      "110.05.20(四)00:50",
      "110.05.19",
      "4038.3",
      "3728.8",
      "309.5",
      "8.30",
      "Y"
    ],
    [
      "2951.2",
      "73",
      "4030.0",
      "3780.0",
      "250.0",
      "6.61",
      "Y",
      "13:00-16:00",
      "110.05.20(四)01:00",
      "110.05.19",
      "4038.3",
      "3728.8",
      "309.5",
      "8.30",
      "Y"
    ],
    [
      "2934.9",
      "72",
      "4030.0",
      "3780.0",
      "250.0",
      "6.61",
      "Y",
      "13:00-16:00",
      "110.05.20(四)01:10",
      "110.05.19",
      "4038.3",
      "3728.8",
      "309.5",
      "8.30",
      "Y"
    ],
    [
      "2896.0",
      "71",
      "4030.0",
      "3780.0",
      "250.0",
      "6.61",
      "Y",
      "13:00-16:00",
      "110.05.20(四)01:20",
      "110.05.19",
      "4038.3",
      "3728.8",
      "309.5",
      "8.30",
      "Y"
    ],
    [
      "2879.1",
      "71",
      "4030.0",
      "3780.0",
      "250.0",
      "6.61",
      "Y",
      "13:00-16:00",
      "110.05.20(四)01:30",
      "110.05.19",
      "4038.3",
      "3728.8",
      "309.5",
      "8.30",
      "Y"
    ],
    [
      "2872.4",
      "71",
      "4030.0",
      "3780.0",
      "250.0",
      "6.61",
      "Y",
      "13:00-16:00",
      "110.05.20(四)01:40",
      "110.05.19",
      "4038.3",
      "3728.8",
      "309.5",
      "8.30",
      "Y"
    ],
    [
      "2868.9",
      "71",
      "4030.0",
      "3780.0",
      "250.0",
      "6.61",
      "Y",
      "13:00-16:00",
      "110.05.20(四)01:50",
      "110.05.19",
      "4038.3",
      "3728.8",
      "309.5",
      "8.30",
      "Y"
    ],
    [
      "2840.1",
      "70",
      "4030.0",
      "3780.0",
      "250.0",
      "6.61",
      "Y",
      "13:00-16:00",
      "110.05.20(四)02:00",
      "110.05.19",
      "4038.3",
      "3728.8",
      "309.5",
      "8.30",
      "Y"
    ],
    [
      "2831.5",
      "70",
      "4030.0",
      "3780.0",
      "250.0",
      "6.61",
      "Y",
      "13:00-16:00",
      "110.05.20(四)02:10",
      "110.05.19",
      "4038.3",
      "3728.8",
      "309.5",
      "8.30",
      "Y"
    ],
    [
      "2798.8",
      "69",
      "4030.0",
      "3780.0",
      "250.0",
      "6.61",
      "Y",
      "13:00-16:00",
      "110.05.20(四)02:20",
      "110.05.19",
      "4038.3",
      "3728.8",
      "309.5",
      "8.30",
      "Y"
    ],
    [
      "2798.7",
      "69",
      "4030.0",
      "3780.0",
      "250.0",
      "6.61",
      "Y",
      "13:00-16:00",
      "110.05.20(四)02:30",
      "110.05.19",
      "4038.3",
      "3728.8",
      "309.5",
      "8.30",
      "Y"
    ],
    [
      "2794.4",
      "69",
      "4030.0",
      "3780.0",
      "250.0",
      "6.61",
      "Y",
      "13:00-16:00",
      "110.05.20(四)02:40",
      "110.05.19",
      "4038.3",
      "3728.8",
      "309.5",
      "8.30",
      "Y"
    ],
    [
      "2774.5",
      "68",
      "4030.0",
      "3780.0",
      "250.0",
      "6.61",
      "Y",
      "13:00-16:00",
      "110.05.20(四)02:50",
      "110.05.19",
      "4038.3",
      "3728.8",
      "309.5",
      "8.30",
      "Y"
    ],
    [
      "2759.7",
      "68",
      "4030.0",
      "3780.0",
      "250.0",
      "6.61",
      "Y",
      "13:00-16:00",
      "110.05.20(四)03:00",
      "110.05.19",
      "4038.3",
      "3728.8",
      "309.5",
      "8.30",
      "Y"
    ]
  ]
}