{"success": "true", "result": { "resource_id": "-" }, "records" : [ {"curr_load" : "3418.8" , "curr_util_rate" : "82"   },{ "fore_maxi_sply_capacity" : "4151.5" , "fore_peak_dema_load" : "3680.0" , "fore_peak_resv_capacity" : "471.5" , "fore_peak_resv_rate" : "12.81" , "fore_peak_resv_indicator" : "G" , "fore_peak_hour_range" : "13:00-16:00" , "publish_time" : "110.08.02(一)14:30"   },{ "yday_date" : "110.08.01" , "yday_maxi_sply_capacity" : "3554.1" , "yday_peak_dema_load" : "3005.5" , "yday_peak_resv_capacity" : "548.7" , "yday_peak_resv_rate" : "18.26" , "yday_peak_resv_indicator" : "G"  },{ "real_hr_maxi_sply_capacity" : "3978.2" , "real_hr_peak_time" : "2021.08.02 03:18" } ]}