{"success": "true", "result": { "resource_id": "-" }, "records" : [ {"curr_load" : "2520.7" , "curr_util_rate" : "62"   },{ "fore_maxi_sply_capacity" : "4060.0" , "fore_peak_dema_load" : "3670.0" , "fore_peak_resv_capacity" : "390.0" , "fore_peak_resv_rate" : "10.63" , "fore_peak_resv_indicator" : "G" , "fore_peak_hour_range" : "13:00-16:00" , "publish_time" : "110.06.21(一)03:20"   },{ "yday_date" : "110.06.20" , "yday_maxi_sply_capacity" : "3851.7" , "yday_peak_dema_load" : "3383.2" , "yday_peak_resv_capacity" : "468.4" , "yday_peak_resv_rate" : "13.85" , "yday_peak_resv_indicator" : "G"  } ] } 